Netio/Device.py
Netio/__init__.py
Netio/__main__.py
Netio/cli.py
Netio/exceptions.py
netio-1.0.13.dist-info/LICENSE
netio-1.0.13.dist-info/METADATA
netio-1.0.13.dist-info/WHEEL
netio-1.0.13.dist-info/entry_points.txt
netio-1.0.13.dist-info/RECORD
