Metadata-Version: 2.1
Name: Netio
Version: 1.0.13
Summary: Interface to control NETIO Products devices
Home-page: https://github.com/netioproducts/PyNetio
License: MIT
Keywords: netio,netio products,power control,power management,power monitoring,power metering,power switching,power switching device,power switching devices,power switching products,power switching products
Author: Adam Verner
Author-email: averner@netio.eu
Requires-Python: >=3.11,<4.0
Classifier: Development Status :: 5 - Production/Stable
Classifier: Intended Audience :: Developers
Classifier: License :: OSI Approved :: MIT License
Classifier: Natural Language :: English
Classifier: Operating System :: OS Independent
Classifier: Programming Language :: Python :: 3
Classifier: Programming Language :: Python :: 3.11
Classifier: Programming Language :: Python :: 3.10
Classifier: Programming Language :: Python :: 3.6
Classifier: Programming Language :: Python :: 3.7
Classifier: Programming Language :: Python :: 3.8
Classifier: Programming Language :: Python :: 3.9
Classifier: Programming Language :: Python :: Implementation :: CPython
Classifier: Programming Language :: Python :: Implementation :: PyPy
Classifier: Topic :: Home Automation
Classifier: Topic :: Software Development :: Libraries :: Python Modules
Classifier: Topic :: System :: Hardware :: Hardware Drivers
Classifier: Topic :: System :: Monitoring
Classifier: Topic :: System :: Power (UPS)
Classifier: Topic :: Utilities
Requires-Dist: pyopenssl (>=23.2.0,<24.0.0)
Requires-Dist: requests (>=2.31.0,<3.0.0)
Project-URL: Repository, https://github.com/netioproducts/PyNetio
